ponika/__init__.py
ponika/models.py
ponika/test_client.py
ponika/endpoints/dhcp.py
ponika/endpoints/gps.py
ponika/endpoints/internet_connection.py
ponika/endpoints/ip_neighbors.py
ponika/endpoints/ip_routes.py
ponika/endpoints/messages.py
ponika/endpoints/modems.py
ponika/endpoints/session.py
ponika/endpoints/tailscale.py
ponika/endpoints/unauthorized.py
ponika/endpoints/wireless.py
ponika-0.4.0.dist-info/METADATA
ponika-0.4.0.dist-info/WHEEL
ponika-0.4.0.dist-info/entry_points.txt
ponika-0.4.0.dist-info/RECORD
