Metadata-Version: 2.4
Name: ponika
Version: 0.4.0
Summary: Teltonika Device API Client
Author-email: Ben Evans <ben@bluechimp.io>
Requires-Python: >=3.13
Requires-Dist: pydantic>=2.11.5
Requires-Dist: requests>=2.32.3
